jotsu/__init__.py
jotsu/mcp/__init__.py
jotsu/mcp/cli/__init__.py
jotsu/mcp/cli/base.py
jotsu/mcp/cli/main.py
jotsu/mcp/cli/utils.py
jotsu/mcp/cli/workflows.py
jotsu/mcp/client/__init__.py
jotsu/mcp/client/client.py
jotsu/mcp/client/credentials.py
jotsu/mcp/client/oauth.py
jotsu/mcp/client/utils.py
jotsu/mcp/local/__init__.py
jotsu/mcp/local/cache.py
jotsu/mcp/local/client.py
jotsu/mcp/local/client_manager.py
jotsu/mcp/local/credentials.py
jotsu/mcp/local/encryption.py
jotsu/mcp/local/localserver.py
jotsu/mcp/server/__init__.py
jotsu/mcp/server/cache.py
jotsu/mcp/server/client_manager.py
jotsu/mcp/server/routes.py
jotsu/mcp/server/utils.py
jotsu/mcp/server/auth/__init__.py
jotsu/mcp/server/auth/base.py
jotsu/mcp/server/auth/pass_thru.py
jotsu/mcp/server/auth/third_party.py
jotsu/mcp/types/__init__.py
jotsu/mcp/types/exceptions.py
jotsu/mcp/types/models.py
jotsu/mcp/types/rules.py
jotsu/mcp/types/shared.py
jotsu/mcp/workflow/__init__.py
jotsu/mcp/workflow/__main__.py
jotsu/mcp/workflow/engine.py
jotsu/mcp/workflow/sessions.py
jotsu/mcp/workflow/utils.py
jotsu/mcp/workflow/handler/__init__.py
jotsu/mcp/workflow/handler/anthropic.py
jotsu/mcp/workflow/handler/cloudflare.py
jotsu/mcp/workflow/handler/function.py
jotsu/mcp/workflow/handler/handler.py
jotsu/mcp/workflow/handler/loop.py
jotsu/mcp/workflow/handler/openai.py
jotsu/mcp/workflow/handler/pick.py
jotsu/mcp/workflow/handler/prompts.py
jotsu/mcp/workflow/handler/resources.py
jotsu/mcp/workflow/handler/script.py
jotsu/mcp/workflow/handler/switch.py
jotsu/mcp/workflow/handler/tools.py
jotsu/mcp/workflow/handler/transform.py
jotsu/mcp/workflow/handler/types.py
jotsu/mcp/workflow/handler/utils.py
jotsu_mcp-0.24.0.dist-info/licenses/LICENSE
jotsu_mcp-0.24.0.dist-info/METADATA
jotsu_mcp-0.24.0.dist-info/WHEEL
jotsu_mcp-0.24.0.dist-info/entry_points.txt
jotsu_mcp-0.24.0.dist-info/top_level.txt
jotsu_mcp-0.24.0.dist-info/RECORD
