Metadata-Version: 2.4
Name: jotsu-mcp
Version: 0.24.0
Summary: Automatation for the Model Context Protocol (MCP).
License:                                  Apache License
Requires-Python: >=3.12
License-File: LICENSE
Requires-Dist: jsonata-python>=0.5.3
Requires-Dist: jsonschema>=4.25.0
Requires-Dist: mcp>=1.13.1
Requires-Dist: pkce>=1.0.3
Requires-Dist: pydantic>=2.6.1
Requires-Dist: pyjwt>=2.10.1
Requires-Dist: python-ulid>=3.1.0
Requires-Dist: asteval>=1.0.6
Requires-Dist: quickjs>=1.19.4
Provides-Extra: cli
Requires-Dist: click>=8.2.1; extra == "cli"
Requires-Dist: aiofiles==24.1.0; extra == "cli"
Requires-Dist: json-with-comments>=1.2.10; extra == "cli"
Requires-Dist: pkce>=1.0.3; extra == "cli"
Requires-Dist: python-ulid>=3.0.0; extra == "cli"
Requires-Dist: python-dotenv>=1.1.0; extra == "cli"
Provides-Extra: anthropic
Requires-Dist: anthropic>=0.57.1; extra == "anthropic"
Requires-Dist: pybars3>=0.9.7; extra == "anthropic"
Provides-Extra: openai
Requires-Dist: openai>=0.101.0; extra == "openai"
Requires-Dist: pybars3>=0.9.7; extra == "openai"
Provides-Extra: cloudflare
Requires-Dist: cloudflare>=4.3.1; extra == "cloudflare"
Requires-Dist: pybars3>=0.9.7; extra == "cloudflare"
Provides-Extra: cryptography
Requires-Dist: cryptography>=46.0.2; extra == "cryptography"
Provides-Extra: dev
Requires-Dist: build>=1.3.0; extra == "dev"
Requires-Dist: flake8>=7.2.0; extra == "dev"
Requires-Dist: flake8-quotes>=3.4.0; extra == "dev"
Requires-Dist: pytest>=8.3.5; extra == "dev"
Requires-Dist: pytest-asyncio>=1.0.0; extra == "dev"
Requires-Dist: pytest-cov>=6.1.1; extra == "dev"
Requires-Dist: pytest-mock>=3.14.1; extra == "dev"
Requires-Dist: setuptools>=80.9.0; extra == "dev"
Requires-Dist: twine>=6.1.0; extra == "dev"
Requires-Dist: pydantic-to-typescript>=2.0.0; extra == "dev"
Dynamic: license-file
